openvoice_cli/__init__.py
openvoice_cli/__main__.py
openvoice_cli/api.py
openvoice_cli/attentions.py
openvoice_cli/commons.py
openvoice_cli/downloader.py
openvoice_cli/mel_processing.py
openvoice_cli/models.py
openvoice_cli/modules.py
openvoice_cli/se_extractor.py
openvoice_cli/transforms.py
openvoice_cli/utils.py
openvoice_cli/checkpoints/base_speakers/ses/en-au.pth
openvoice_cli/checkpoints/base_speakers/ses/en-br.pth
openvoice_cli/checkpoints/base_speakers/ses/en-default.pth
openvoice_cli/checkpoints/base_speakers/ses/en-india.pth
openvoice_cli/checkpoints/base_speakers/ses/en-newest.pth
openvoice_cli/checkpoints/base_speakers/ses/en-us.pth
openvoice_cli/checkpoints/base_speakers/ses/es.pth
openvoice_cli/checkpoints/base_speakers/ses/fr.pth
openvoice_cli/checkpoints/base_speakers/ses/jp.pth
openvoice_cli/checkpoints/base_speakers/ses/kr.pth
openvoice_cli/checkpoints/base_speakers/ses/zh.pth
openvoice_cli-0.0.5.dist-info/METADATA
openvoice_cli-0.0.5.dist-info/WHEEL
openvoice_cli-0.0.5.dist-info/RECORD
