Metadata-Version: 2.1
Name: openvoice-cli
Version: 0.0.5
Summary: Use OpenVoice 2 stage via console or python scripts
Project-URL: Homepage, https://github.com/daswer123/OpenVoice-cli
Project-URL: Bug Tracker, https://github.com/daswer123/OpenVoice-cli/issues
Author-email: daswer123 <daswerq123@gmail.com>
Classifier: License :: OSI Approved :: MIT License
Classifier: Operating System :: OS Independent
Classifier: Programming Language :: Python :: 3
Requires-Python: >=3.9
Requires-Dist: faster-whisper>=0.9.0
Requires-Dist: librosa==0.9.1
Requires-Dist: numpy>1.24.2
Requires-Dist: pydub==0.25.1
Requires-Dist: torch>=1.13.1
Requires-Dist: torchaudio>=0.13.1
Requires-Dist: typing-extensions>=4.6.1
Requires-Dist: wavmark==0.0.3
Requires-Dist: whisper-timestamped>=1.14.2
